pu4c/__init__.py
pu4c/config.py
pu4c/common/__init__.py
pu4c/common/app.py
pu4c/common/utils/__init__.py
pu4c/common/utils/common_utils.py
pu4c/cv/__init__.py
pu4c/cv/app.py
pu4c/cv/utils/__init__.py
pu4c/cv/utils/color_utils.py
pu4c/cv/utils/common_utils.py
pu4c/cv/utils/cv2_utils.py
pu4c/cv/utils/det3d_utils.py
pu4c/cv/utils/image_utils.py
pu4c/cv/utils/open3d_utils.py
pu4c/cv/utils/pointcloud_utils.py
pu4c-1.3.1.dist-info/LICENSE
pu4c-1.3.1.dist-info/METADATA
pu4c-1.3.1.dist-info/WHEEL
pu4c-1.3.1.dist-info/top_level.txt
pu4c-1.3.1.dist-info/RECORD
